paven/__init__.py
paven/__main__.py
paven/cleanup.py
paven/configuration.py
paven/sync.py
paven/utils.py
paven/vendor.py
paven-0.1.2.dist-info/licenses/LICENSE
paven-0.1.2.dist-info/METADATA
paven-0.1.2.dist-info/WHEEL
paven-0.1.2.dist-info/top_level.txt
paven-0.1.2.dist-info/RECORD
